intellienv/__init__.py
intellienv/__main__.py
intellienv/core.py
intellienv-0.1.1.dist-info/licenses/LICENSE
intellienv-0.1.1.dist-info/METADATA
intellienv-0.1.1.dist-info/WHEEL
intellienv-0.1.1.dist-info/entry_points.txt
intellienv-0.1.1.dist-info/top_level.txt
intellienv-0.1.1.dist-info/RECORD
