Metadata-Version: 2.4
Name: intellienv
Version: 0.1.1
Summary: A Python package for managing environment variables safely and conveniently
Home-page: https://github.com/AdiNairCS50/intellienv
Author: Adithya Nair
Author-email: 66921216+AdiNairCS50@users.noreply.github.com
License: MIT
Project-URL: Bug Tracker, https://github.com/AdiNairCS50/intellienv/issues
Project-URL: Documentation, https://github.com/AdiNairCS50/intellienv#readme
Project-URL: Source Code, https://github.com/AdiNairCS50/intellienv
Keywords: environment,variables,configuration,dotenv,env,config
Classifier: Development Status :: 3 - Alpha
Classifier: Intended Audience :: Developers
Classifier: License :: OSI Approved :: MIT License
Classifier: Programming Language :: Python :: 3
Classifier: Programming Language :: Python :: 3.6
Classifier: Programming Language :: Python :: 3.7
Classifier: Programming Language :: Python :: 3.8
Classifier: Programming Language :: Python :: 3.9
Requires-Python: >=3.6
License-File: LICENSE
Dynamic: author
Dynamic: author-email
Dynamic: classifier
Dynamic: description
Dynamic: description-content-type
Dynamic: home-page
Dynamic: keywords
Dynamic: license
Dynamic: license-file
Dynamic: project-url
Dynamic: requires-python
Dynamic: summary
